[
  {
    "id": "militia",
    "name": "Militia",
    "class": "infantry",
    "hp": 40,
    "attack": 4,
    "meleeArmor": 0,
    "pierceArmor": 1,
    "range": 0,
    "speed": 0.9,
    "attackBonuses": [],
    "armorClasses": ["infantry"],
    "cost": { "food": 60, "wood": 0, "gold": 20 },
    "trainingTime": 21
  },
  {
    "id": "man_at_arms",
    "name": "Man-at-Arms",
    "class": "infantry",
    "hp": 45,
    "attack": 6,
    "meleeArmor": 0,
    "pierceArmor": 1,
    "range": 0,
    "speed": 0.9,
    "attackBonuses": [{"class": "eagle", "bonus": 2}],
    "armorClasses": ["infantry"],
    "cost": { "food": 60, "wood": 0, "gold": 20 },
    "trainingTime": 21
  },
  {
    "id": "long_swordsman",
    "name": "Long Swordsman",
    "class": "infantry",
    "hp": 60,
    "attack": 9,
    "meleeArmor": 0,
    "pierceArmor": 1,
    "range": 0,
    "speed": 0.9,
    "attackBonuses": [{"class": "eagle", "bonus": 6}],
    "armorClasses": ["infantry"],
    "cost": { "food": 60, "wood": 0, "gold": 20 },
    "trainingTime": 21
  },
  {
    "id": "two_handed_swordsman",
    "name": "Two-Handed Swordsman",
    "class": "infantry",
    "hp": 60,
    "attack": 12,
    "meleeArmor": 0,
    "pierceArmor": 1,
    "range": 0,
    "speed": 0.9,
    "attackBonuses": [{"class": "eagle", "bonus": 8}],
    "armorClasses": ["infantry"],
    "cost": { "food": 60, "wood": 0, "gold": 20 },
    "trainingTime": 21
  },
  {
    "id": "champion",
    "name": "Champion",
    "class": "infantry",
    "hp": 70,
    "attack": 13,
    "meleeArmor": 1,
    "pierceArmor": 1,
    "range": 0,
    "speed": 0.9,
    "attackBonuses": [{"class": "eagle", "bonus": 8}],
    "armorClasses": ["infantry"],
    "cost": { "food": 60, "wood": 0, "gold": 20 },
    "trainingTime": 21
  },
  {
    "id": "spearman",
    "name": "Spearman",
    "class": "infantry",
    "hp": 45,
    "attack": 3,
    "meleeArmor": 0,
    "pierceArmor": 0,
    "range": 0,
    "speed": 1.0,
    "attackBonuses": [{"class": "cavalry", "bonus": 15}, {"class": "war_elephant", "bonus": 15}, {"class": "camel", "bonus": 12}, {"class": "ship", "bonus": 9}],
    "armorClasses": ["infantry", "spearman"],
    "cost": { "food": 35, "wood": 25, "gold": 0 },
    "trainingTime": 22
  },
  {
    "id": "pikeman",
    "name": "Pikeman",
    "class": "infantry",
    "hp": 55,
    "attack": 4,
    "meleeArmor": 0,
    "pierceArmor": 0,
    "range": 0,
    "speed": 1.0,
    "attackBonuses": [{"class": "cavalry", "bonus": 22}, {"class": "war_elephant", "bonus": 25}, {"class": "camel", "bonus": 18}, {"class": "ship", "bonus": 16}],
    "armorClasses": ["infantry", "spearman"],
    "cost": { "food": 35, "wood": 25, "gold": 0 },
    "trainingTime": 22
  },
  {
    "id": "halberdier",
    "name": "Halberdier",
    "class": "infantry",
    "hp": 60,
    "attack": 6,
    "meleeArmor": 0,
    "pierceArmor": 0,
    "range": 0,
    "speed": 1.0,
    "attackBonuses": [{"class": "cavalry", "bonus": 32}, {"class": "war_elephant", "bonus": 28}, {"class": "camel", "bonus": 26}, {"class": "ship", "bonus": 17}],
    "armorClasses": ["infantry", "spearman"],
    "cost": { "food": 35, "wood": 25, "gold": 0 },
    "trainingTime": 22
  },
  {
    "id": "eagle_scout",
    "name": "Eagle Scout",
    "class": "infantry",
    "hp": 50,
    "attack": 4,
    "meleeArmor": 0,
    "pierceArmor": 2,
    "range": 0,
    "speed": 1.1,
    "attackBonuses": [{"class": "monk", "bonus": 8}, {"class": "siege", "bonus": 3}],
    "armorClasses": ["infantry", "eagle"],
    "cost": { "food": 20, "wood": 0, "gold": 50 },
    "trainingTime": 35
  },
  {
    "id": "eagle_warrior",
    "name": "Eagle Warrior",
    "class": "infantry",
    "hp": 55,
    "attack": 7,
    "meleeArmor": 0,
    "pierceArmor": 3,
    "range": 0,
    "speed": 1.15,
    "attackBonuses": [{"class": "monk", "bonus": 8}, {"class": "siege", "bonus": 3}],
    "armorClasses": ["infantry", "eagle"],
    "cost": { "food": 20, "wood": 0, "gold": 50 },
    "trainingTime": 35
  },
  {
    "id": "elite_eagle_warrior",
    "name": "Elite Eagle Warrior",
    "class": "infantry",
    "hp": 60,
    "attack": 9,
    "meleeArmor": 0,
    "pierceArmor": 4,
    "range": 0,
    "speed": 1.3,
    "attackBonuses": [{"class": "monk", "bonus": 10}, {"class": "siege", "bonus": 5}],
    "armorClasses": ["infantry", "eagle"],
    "cost": { "food": 20, "wood": 0, "gold": 50 },
    "trainingTime": 20
  },
  {
    "id": "condottiero",
    "name": "Condottiero",
    "class": "infantry",
    "hp": 80,
    "attack": 10,
    "meleeArmor": 1,
    "pierceArmor": 0,
    "range": 0,
    "speed": 1.2,
    "attackBonuses": [{"class": "gunpowder", "bonus": 10}],
    "armorClasses": ["infantry", "condottiero"],
    "cost": { "food": 50, "wood": 0, "gold": 35 },
    "trainingTime": 18
  },
  {
    "id": "archer",
    "name": "Archer",
    "class": "archer",
    "hp": 30,
    "attack": 4,
    "meleeArmor": 0,
    "pierceArmor": 0,
    "range": 4,
    "speed": 0.96,
    "attackBonuses": [{"class": "spearman", "bonus": 3}],
    "armorClasses": ["archer"],
    "cost": { "food": 0, "wood": 25, "gold": 45 },
    "trainingTime": 35
  },
  {
    "id": "crossbowman",
    "name": "Crossbowman",
    "class": "archer",
    "hp": 35,
    "attack": 5,
    "meleeArmor": 0,
    "pierceArmor": 0,
    "range": 5,
    "speed": 0.96,
    "attackBonuses": [{"class": "spearman", "bonus": 3}],
    "armorClasses": ["archer"],
    "cost": { "food": 0, "wood": 25, "gold": 45 },
    "trainingTime": 27
  },
  {
    "id": "arbalester",
    "name": "Arbalester",
    "class": "archer",
    "hp": 40,
    "attack": 6,
    "meleeArmor": 0,
    "pierceArmor": 0,
    "range": 5,
    "speed": 0.96,
    "attackBonuses": [{"class": "spearman", "bonus": 3}],
    "armorClasses": ["archer"],
    "cost": { "food": 0, "wood": 25, "gold": 45 },
    "trainingTime": 27
  },
  {
    "id": "skirmisher",
    "name": "Skirmisher",
    "class": "archer",
    "hp": 30,
    "attack": 2,
    "meleeArmor": 0,
    "pierceArmor": 3,
    "range": 4,
    "speed": 0.96,
    "attackBonuses": [{"class": "archer", "bonus": 3}, {"class": "spearman", "bonus": 3}],
    "armorClasses": ["archer"],
    "cost": { "food": 25, "wood": 35, "gold": 0 },
    "trainingTime": 22
  },
  {
    "id": "elite_skirmisher",
    "name": "Elite Skirmisher",
    "class": "archer",
    "hp": 35,
    "attack": 3,
    "meleeArmor": 0,
    "pierceArmor": 4,
    "range": 5,
    "speed": 0.96,
    "attackBonuses": [{"class": "archer", "bonus": 4}, {"class": "spearman", "bonus": 3}, {"class": "cavalry_archer", "bonus": 2}],
    "armorClasses": ["archer"],
    "cost": { "food": 25, "wood": 35, "gold": 0 },
    "trainingTime": 22
  },
  {
    "id": "imperial_skirmisher",
    "name": "Imperial Skirmisher",
    "class": "archer",
    "hp": 35,
    "attack": 4,
    "meleeArmor": 0,
    "pierceArmor": 5,
    "range": 5,
    "speed": 0.96,
    "attackBonuses": [{"class": "archer", "bonus": 5}, {"class": "spearman", "bonus": 3}, {"class": "cavalry_archer", "bonus": 3}],
    "armorClasses": ["archer"],
    "cost": { "food": 25, "wood": 35, "gold": 0 },
    "trainingTime": 22
  },
  {
    "id": "cavalry_archer",
    "name": "Cavalry Archer",
    "class": "archer",
    "hp": 50,
    "attack": 6,
    "meleeArmor": 0,
    "pierceArmor": 0,
    "range": 4,
    "speed": 1.4,
    "attackBonuses": [{"class": "spearman", "bonus": 2}],
    "armorClasses": ["archer", "cavalry_archer", "cavalry"],
    "cost": { "food": 0, "wood": 40, "gold": 60 },
    "trainingTime": 34
  },
  {
    "id": "heavy_cav_archer",
    "name": "Heavy Cavalry Archer",
    "class": "archer",
    "hp": 60,
    "attack": 7,
    "meleeArmor": 1,
    "pierceArmor": 0,
    "range": 4,
    "speed": 1.4,
    "attackBonuses": [{"class": "spearman", "bonus": 2}],
    "armorClasses": ["archer", "cavalry_archer", "cavalry"],
    "cost": { "food": 0, "wood": 40, "gold": 60 },
    "trainingTime": 27
  },
  {
    "id": "hand_cannoneer",
    "name": "Hand Cannoneer",
    "class": "archer",
    "hp": 35,
    "attack": 17,
    "meleeArmor": 1,
    "pierceArmor": 0,
    "range": 7,
    "speed": 0.96,
    "attackBonuses": [{"class": "infantry", "bonus": 10}, {"class": "spearman", "bonus": 1}],
    "armorClasses": ["archer", "gunpowder"],
    "cost": { "food": 45, "wood": 0, "gold": 50 },
    "trainingTime": 34,
    "special": "Inaccurate (65%)"
  },
  {
    "id": "slinger",
    "name": "Slinger",
    "class": "archer",
    "hp": 40,
    "attack": 5,
    "meleeArmor": 0,
    "pierceArmor": 0,
    "range": 5,
    "speed": 0.96,
    "attackBonuses": [{"class": "infantry", "bonus": 10}, {"class": "spearman", "bonus": 3}, {"class": "condottiero", "bonus": 10}],
    "armorClasses": ["archer"],
    "cost": { "food": 30, "wood": 0, "gold": 40 },
    "trainingTime": 25
  },
  {
    "id": "scout_cavalry",
    "name": "Scout Cavalry",
    "class": "cavalry",
    "hp": 45,
    "attack": 5,
    "meleeArmor": 0,
    "pierceArmor": 2,
    "range": 0,
    "speed": 1.55,
    "attackBonuses": [{"class": "monk", "bonus": 6}],
    "armorClasses": ["cavalry"],
    "cost": { "food": 80, "wood": 0, "gold": 0 },
    "trainingTime": 30
  },
  {
    "id": "light_cavalry",
    "name": "Light Cavalry",
    "class": "cavalry",
    "hp": 60,
    "attack": 7,
    "meleeArmor": 0,
    "pierceArmor": 2,
    "range": 0,
    "speed": 1.5,
    "attackBonuses": [{"class": "monk", "bonus": 10}],
    "armorClasses": ["cavalry"],
    "cost": { "food": 80, "wood": 0, "gold": 0 },
    "trainingTime": 30
  },
  {
    "id": "hussar",
    "name": "Hussar",
    "class": "cavalry",
    "hp": 75,
    "attack": 7,
    "meleeArmor": 0,
    "pierceArmor": 2,
    "range": 0,
    "speed": 1.5,
    "attackBonuses": [{"class": "monk", "bonus": 12}],
    "armorClasses": ["cavalry"],
    "cost": { "food": 80, "wood": 0, "gold": 0 },
    "trainingTime": 30
  },
  {
    "id": "winged_hussar",
    "name": "Winged Hussar",
    "class": "cavalry",
    "hp": 80,
    "attack": 9,
    "meleeArmor": 0,
    "pierceArmor": 2,
    "range": 0,
    "speed": 1.5,
    "attackBonuses": [{"class": "monk", "bonus": 12}, {"class": "siege", "bonus": 5}],
    "armorClasses": ["cavalry"],
    "cost": { "food": 80, "wood": 0, "gold": 0 },
    "trainingTime": 30
  },
  {
    "id": "knight",
    "name": "Knight",
    "class": "cavalry",
    "hp": 100,
    "attack": 10,
    "meleeArmor": 2,
    "pierceArmor": 2,
    "range": 0,
    "speed": 1.35,
    "attackBonuses": [],
    "armorClasses": ["cavalry"],
    "cost": { "food": 60, "wood": 0, "gold": 75 },
    "trainingTime": 30
  },
  {
    "id": "cavalier",
    "name": "Cavalier",
    "class": "cavalry",
    "hp": 120,
    "attack": 12,
    "meleeArmor": 2,
    "pierceArmor": 2,
    "range": 0,
    "speed": 1.35,
    "attackBonuses": [],
    "armorClasses": ["cavalry"],
    "cost": { "food": 60, "wood": 0, "gold": 75 },
    "trainingTime": 30
  },
  {
    "id": "paladin",
    "name": "Paladin",
    "class": "cavalry",
    "hp": 160,
    "attack": 14,
    "meleeArmor": 2,
    "pierceArmor": 3,
    "range": 0,
    "speed": 1.35,
    "attackBonuses": [],
    "armorClasses": ["cavalry"],
    "cost": { "food": 60, "wood": 0, "gold": 75 },
    "trainingTime": 30
  },
  {
    "id": "camel_rider",
    "name": "Camel Rider",
    "class": "cavalry",
    "hp": 100,
    "attack": 6,
    "meleeArmor": 0,
    "pierceArmor": 0,
    "range": 0,
    "speed": 1.45,
    "attackBonuses": [{"class": "cavalry", "bonus": 9}, {"class": "camel", "bonus": 5}, {"class": "ship", "bonus": 5}],
    "armorClasses": ["camel"],
    "cost": { "food": 55, "wood": 0, "gold": 60 },
    "trainingTime": 22
  },
  {
    "id": "heavy_camel_rider",
    "name": "Heavy Camel Rider",
    "class": "cavalry",
    "hp": 120,
    "attack": 7,
    "meleeArmor": 0,
    "pierceArmor": 0,
    "range": 0,
    "speed": 1.45,
    "attackBonuses": [{"class": "cavalry", "bonus": 18}, {"class": "camel", "bonus": 9}, {"class": "ship", "bonus": 9}],
    "armorClasses": ["camel"],
    "cost": { "food": 55, "wood": 0, "gold": 60 },
    "trainingTime": 22
  },
  {
    "id": "imperial_camel_rider",
    "name": "Imperial Camel Rider",
    "class": "cavalry",
    "hp": 140,
    "attack": 8,
    "meleeArmor": 0,
    "pierceArmor": 0,
    "range": 0,
    "speed": 1.45,
    "attackBonuses": [{"class": "cavalry", "bonus": 18}, {"class": "camel", "bonus": 9}, {"class": "ship", "bonus": 9}],
    "armorClasses": ["camel"],
    "cost": { "food": 55, "wood": 0, "gold": 60 },
    "trainingTime": 22
  },
  {
    "id": "battle_elephant",
    "name": "Battle Elephant",
    "class": "cavalry",
    "hp": 250,
    "attack": 12,
    "meleeArmor": 1,
    "pierceArmor": 2,
    "range": 0,
    "speed": 0.85,
    "attackBonuses": [{"class": "building", "bonus": 7}],
    "armorClasses": ["cavalry", "war_elephant"],
    "cost": { "food": 120, "wood": 0, "gold": 70 },
    "trainingTime": 28
  },
  {
    "id": "elite_battle_elephant",
    "name": "Elite Battle Elephant",
    "class": "cavalry",
    "hp": 300,
    "attack": 14,
    "meleeArmor": 1,
    "pierceArmor": 3,
    "range": 0,
    "speed": 0.85,
    "attackBonuses": [{"class": "building", "bonus": 10}],
    "armorClasses": ["cavalry", "war_elephant"],
    "cost": { "food": 120, "wood": 0, "gold": 70 },
    "trainingTime": 28
  },
  {
    "id": "steppe_lancer",
    "name": "Steppe Lancer",
    "class": "cavalry",
    "hp": 60,
    "attack": 9,
    "meleeArmor": 0,
    "pierceArmor": 1,
    "range": 1,
    "speed": 1.45,
    "attackBonuses": [],
    "armorClasses": ["cavalry"],
    "cost": { "food": 70, "wood": 0, "gold": 40 },
    "trainingTime": 20
  },
  {
    "id": "elite_steppe_lancer",
    "name": "Elite Steppe Lancer",
    "class": "cavalry",
    "hp": 80,
    "attack": 11,
    "meleeArmor": 0,
    "pierceArmor": 1,
    "range": 1,
    "speed": 1.45,
    "attackBonuses": [],
    "armorClasses": ["cavalry"],
    "cost": { "food": 70, "wood": 0, "gold": 40 },
    "trainingTime": 20
  },
  {
    "id": "battering_ram",
    "name": "Battering Ram",
    "class": "siege",
    "hp": 175,
    "attack": 2,
    "meleeArmor": -3,
    "pierceArmor": 180,
    "range": 0,
    "speed": 0.5,
    "attackBonuses": [{"class": "building", "bonus": 125}, {"class": "siege", "bonus": 40}],
    "armorClasses": ["siege", "ram"],
    "cost": { "food": 0, "wood": 160, "gold": 75 },
    "trainingTime": 36
  },
  {
    "id": "capped_ram",
    "name": "Capped Ram",
    "class": "siege",
    "hp": 200,
    "attack": 3,
    "meleeArmor": -3,
    "pierceArmor": 190,
    "range": 0,
    "speed": 0.5,
    "attackBonuses": [{"class": "building", "bonus": 150}, {"class": "siege", "bonus": 50}],
    "armorClasses": ["siege", "ram"],
    "cost": { "food": 0, "wood": 160, "gold": 75 },
    "trainingTime": 36
  },
  {
    "id": "siege_ram",
    "name": "Siege Ram",
    "class": "siege",
    "hp": 270,
    "attack": 4,
    "meleeArmor": -3,
    "pierceArmor": 195,
    "range": 0,
    "speed": 0.6,
    "attackBonuses": [{"class": "building", "bonus": 200}, {"class": "siege", "bonus": 65}],
    "armorClasses": ["siege", "ram"],
    "cost": { "food": 0, "wood": 160, "gold": 75 },
    "trainingTime": 36
  },
  {
    "id": "mangonel",
    "name": "Mangonel",
    "class": "siege",
    "hp": 50,
    "attack": 40,
    "meleeArmor": 0,
    "pierceArmor": 6,
    "range": 7,
    "speed": 0.6,
    "attackBonuses": [{"class": "building", "bonus": 12}, {"class": "siege", "bonus": 12}],
    "armorClasses": ["siege"],
    "cost": { "food": 0, "wood": 160, "gold": 135 },
    "trainingTime": 46,
    "special": "Area damage"
  },
  {
    "id": "onager",
    "name": "Onager",
    "class": "siege",
    "hp": 60,
    "attack": 50,
    "meleeArmor": 0,
    "pierceArmor": 7,
    "range": 8,
    "speed": 0.6,
    "attackBonuses": [{"class": "building", "bonus": 12}, {"class": "siege", "bonus": 12}],
    "armorClasses": ["siege"],
    "cost": { "food": 0, "wood": 160, "gold": 135 },
    "trainingTime": 46,
    "special": "Area damage"
  },
  {
    "id": "siege_onager",
    "name": "Siege Onager",
    "class": "siege",
    "hp": 70,
    "attack": 75,
    "meleeArmor": 0,
    "pierceArmor": 8,
    "range": 8,
    "speed": 0.6,
    "attackBonuses": [{"class": "building", "bonus": 12}, {"class": "siege", "bonus": 12}],
    "armorClasses": ["siege"],
    "cost": { "food": 0, "wood": 160, "gold": 135 },
    "trainingTime": 46,
    "special": "Area damage, cuts trees"
  },
  {
    "id": "scorpion",
    "name": "Scorpion",
    "class": "siege",
    "hp": 40,
    "attack": 12,
    "meleeArmor": 0,
    "pierceArmor": 6,
    "range": 7,
    "speed": 0.65,
    "attackBonuses": [{"class": "war_elephant", "bonus": 6}, {"class": "ram", "bonus": 1}],
    "armorClasses": ["siege"],
    "cost": { "food": 0, "wood": 75, "gold": 75 },
    "trainingTime": 30,
    "special": "Pass-through bolt"
  },
  {
    "id": "heavy_scorpion",
    "name": "Heavy Scorpion",
    "class": "siege",
    "hp": 50,
    "attack": 16,
    "meleeArmor": 0,
    "pierceArmor": 7,
    "range": 7,
    "speed": 0.65,
    "attackBonuses": [{"class": "war_elephant", "bonus": 8}, {"class": "ram", "bonus": 2}, {"class": "building", "bonus": 1}],
    "armorClasses": ["siege"],
    "cost": { "food": 0, "wood": 75, "gold": 75 },
    "trainingTime": 30,
    "special": "Pass-through bolt"
  },
  {
    "id": "bombard_cannon",
    "name": "Bombard Cannon",
    "class": "siege",
    "hp": 80,
    "attack": 40,
    "meleeArmor": 2,
    "pierceArmor": 5,
    "range": 12,
    "speed": 0.7,
    "attackBonuses": [{"class": "building", "bonus": 200}, {"class": "ship", "bonus": 40}, {"class": "siege", "bonus": 20}],
    "armorClasses": ["siege", "gunpowder"],
    "cost": { "food": 0, "wood": 225, "gold": 225 },
    "trainingTime": 56,
    "special": "Inaccurate vs moving targets"
  },
  {
    "id": "siege_tower",
    "name": "Siege Tower",
    "class": "siege",
    "hp": 220,
    "attack": 0,
    "meleeArmor": -2,
    "pierceArmor": 100,
    "range": 0,
    "speed": 0.8,
    "attackBonuses": [],
    "armorClasses": ["siege"],
    "cost": { "food": 0, "wood": 200, "gold": 160 },
    "trainingTime": 36,
    "special": "Garrison infantry to bypass walls"
  },
  {
    "id": "trebuchet",
    "name": "Trebuchet",
    "class": "siege",
    "hp": 150,
    "attack": 200,
    "meleeArmor": 1,
    "pierceArmor": 150,
    "range": 16,
    "speed": 0.8,
    "attackBonuses": [{"class": "building", "bonus": 250}],
    "armorClasses": ["siege"],
    "cost": { "food": 0, "wood": 200, "gold": 200 },
    "trainingTime": 50,
    "special": "Must unpack to fire, minimum range 5"
  },
  {
    "id": "monk",
    "name": "Monk",
    "class": "monk",
    "hp": 30,
    "attack": 0,
    "meleeArmor": 0,
    "pierceArmor": 0,
    "range": 9,
    "speed": 0.7,
    "attackBonuses": [],
    "armorClasses": ["monk"],
    "cost": { "food": 0, "wood": 0, "gold": 100 },
    "trainingTime": 51,
    "special": "Converts enemy units, heals allies"
  },
  {
    "id": "missionary",
    "name": "Missionary",
    "class": "monk",
    "hp": 30,
    "attack": 0,
    "meleeArmor": 0,
    "pierceArmor": 0,
    "range": 7,
    "speed": 1.1,
    "attackBonuses": [],
    "armorClasses": ["monk"],
    "cost": { "food": 0, "wood": 0, "gold": 100 },
    "trainingTime": 51,
    "special": "Mounted monk, cannot pick up relics"
  },
  {
    "id": "longbowman",
    "name": "Longbowman",
    "class": "archer",
    "hp": 35,
    "attack": 6,
    "meleeArmor": 0,
    "pierceArmor": 0,
    "range": 5,
    "speed": 0.96,
    "attackBonuses": [{"class": "spearman", "bonus": 3}],
    "armorClasses": ["archer", "unique"],
    "cost": { "food": 0, "wood": 35, "gold": 40 },
    "trainingTime": 19,
    "unique_to": "britons"
  },
  {
    "id": "elite_longbowman",
    "name": "Elite Longbowman",
    "class": "archer",
    "hp": 40,
    "attack": 7,
    "meleeArmor": 0,
    "pierceArmor": 1,
    "range": 6,
    "speed": 0.96,
    "attackBonuses": [{"class": "spearman", "bonus": 3}],
    "armorClasses": ["archer", "unique"],
    "cost": { "food": 0, "wood": 35, "gold": 40 },
    "trainingTime": 19,
    "unique_to": "britons"
  },
  {
    "id": "throwing_axeman",
    "name": "Throwing Axeman",
    "class": "infantry",
    "hp": 50,
    "attack": 7,
    "meleeArmor": 0,
    "pierceArmor": 0,
    "range": 3,
    "speed": 1.0,
    "attackBonuses": [],
    "armorClasses": ["infantry", "unique"],
    "cost": { "food": 55, "wood": 0, "gold": 25 },
    "trainingTime": 17,
    "unique_to": "franks"
  },
  {
    "id": "elite_throwing_axeman",
    "name": "Elite Throwing Axeman",
    "class": "infantry",
    "hp": 60,
    "attack": 8,
    "meleeArmor": 1,
    "pierceArmor": 0,
    "range": 4,
    "speed": 1.0,
    "attackBonuses": [],
    "armorClasses": ["infantry", "unique"],
    "cost": { "food": 55, "wood": 0, "gold": 25 },
    "trainingTime": 17,
    "unique_to": "franks"
  },
  {
    "id": "teutonic_knight",
    "name": "Teutonic Knight",
    "class": "infantry",
    "hp": 80,
    "attack": 12,
    "meleeArmor": 5,
    "pierceArmor": 2,
    "range": 0,
    "speed": 0.65,
    "attackBonuses": [],
    "armorClasses": ["infantry", "unique"],
    "cost": { "food": 85, "wood": 0, "gold": 40 },
    "trainingTime": 12,
    "unique_to": "teutons"
  },
  {
    "id": "elite_teutonic_knight",
    "name": "Elite Teutonic Knight",
    "class": "infantry",
    "hp": 100,
    "attack": 17,
    "meleeArmor": 10,
    "pierceArmor": 2,
    "range": 0,
    "speed": 0.65,
    "attackBonuses": [],
    "armorClasses": ["infantry", "unique"],
    "cost": { "food": 85, "wood": 0, "gold": 40 },
    "trainingTime": 12,
    "unique_to": "teutons"
  },
  {
    "id": "mangudai",
    "name": "Mangudai",
    "class": "archer",
    "hp": 60,
    "attack": 6,
    "meleeArmor": 0,
    "pierceArmor": 0,
    "range": 4,
    "speed": 1.4,
    "attackBonuses": [{"class": "siege", "bonus": 3}, {"class": "spearman", "bonus": 1}],
    "armorClasses": ["archer", "cavalry_archer", "cavalry", "unique"],
    "cost": { "food": 0, "wood": 55, "gold": 65 },
    "trainingTime": 26,
    "unique_to": "mongols"
  },
  {
    "id": "elite_mangudai",
    "name": "Elite Mangudai",
    "class": "archer",
    "hp": 60,
    "attack": 8,
    "meleeArmor": 1,
    "pierceArmor": 0,
    "range": 4,
    "speed": 1.4,
    "attackBonuses": [{"class": "siege", "bonus": 5}, {"class": "spearman", "bonus": 1}],
    "armorClasses": ["archer", "cavalry_archer", "cavalry", "unique"],
    "cost": { "food": 0, "wood": 55, "gold": 65 },
    "trainingTime": 26,
    "unique_to": "mongols"
  },
  {
    "id": "cataphract",
    "name": "Cataphract",
    "class": "cavalry",
    "hp": 110,
    "attack": 9,
    "meleeArmor": 2,
    "pierceArmor": 1,
    "range": 0,
    "speed": 1.35,
    "attackBonuses": [{"class": "infantry", "bonus": 9}],
    "armorClasses": ["cavalry", "unique"],
    "cost": { "food": 70, "wood": 0, "gold": 75 },
    "trainingTime": 20,
    "unique_to": "byzantines",
    "special": "Resists anti-cavalry bonus damage"
  },
  {
    "id": "elite_cataphract",
    "name": "Elite Cataphract",
    "class": "cavalry",
    "hp": 150,
    "attack": 12,
    "meleeArmor": 2,
    "pierceArmor": 1,
    "range": 0,
    "speed": 1.35,
    "attackBonuses": [{"class": "infantry", "bonus": 12}],
    "armorClasses": ["cavalry", "unique"],
    "cost": { "food": 70, "wood": 0, "gold": 75 },
    "trainingTime": 20,
    "unique_to": "byzantines",
    "special": "Resists anti-cavalry bonus damage"
  },
  {
    "id": "mameluke",
    "name": "Mameluke",
    "class": "cavalry",
    "hp": 65,
    "attack": 7,
    "meleeArmor": 0,
    "pierceArmor": 0,
    "range": 3,
    "speed": 1.4,
    "attackBonuses": [{"class": "cavalry", "bonus": 9}],
    "armorClasses": ["archer", "camel", "unique"],
    "cost": { "food": 55, "wood": 0, "gold": 85 },
    "trainingTime": 23,
    "unique_to": "saracens"
  },
  {
    "id": "elite_mameluke",
    "name": "Elite Mameluke",
    "class": "cavalry",
    "hp": 80,
    "attack": 10,
    "meleeArmor": 1,
    "pierceArmor": 0,
    "range": 3,
    "speed": 1.4,
    "attackBonuses": [{"class": "cavalry", "bonus": 12}],
    "armorClasses": ["archer", "camel", "unique"],
    "cost": { "food": 55, "wood": 0, "gold": 85 },
    "trainingTime": 23,
    "unique_to": "saracens"
  },
  {
    "id": "woad_raider",
    "name": "Woad Raider",
    "class": "infantry",
    "hp": 65,
    "attack": 8,
    "meleeArmor": 0,
    "pierceArmor": 1,
    "range": 0,
    "speed": 1.2,
    "attackBonuses": [{"class": "eagle", "bonus": 2}, {"class": "building", "bonus": 2}],
    "armorClasses": ["infantry", "unique"],
    "cost": { "food": 65, "wood": 0, "gold": 25 },
    "trainingTime": 10,
    "unique_to": "celts"
  },
  {
    "id": "elite_woad_raider",
    "name": "Elite Woad Raider",
    "class": "infantry",
    "hp": 80,
    "attack": 13,
    "meleeArmor": 0,
    "pierceArmor": 1,
    "range": 0,
    "speed": 1.2,
    "attackBonuses": [{"class": "eagle", "bonus": 3}, {"class": "building", "bonus": 3}],
    "armorClasses": ["infantry", "unique"],
    "cost": { "food": 65, "wood": 0, "gold": 25 },
    "trainingTime": 10,
    "unique_to": "celts"
  },
  {
    "id": "samurai",
    "name": "Samurai",
    "class": "infantry",
    "hp": 60,
    "attack": 8,
    "meleeArmor": 1,
    "pierceArmor": 1,
    "range": 0,
    "speed": 1.0,
    "attackBonuses": [{"class": "unique", "bonus": 10}],
    "armorClasses": ["infantry", "unique"],
    "cost": { "food": 60, "wood": 0, "gold": 30 },
    "trainingTime": 9,
    "unique_to": "japanese"
  },
  {
    "id": "elite_samurai",
    "name": "Elite Samurai",
    "class": "infantry",
    "hp": 80,
    "attack": 12,
    "meleeArmor": 1,
    "pierceArmor": 1,
    "range": 0,
    "speed": 1.0,
    "attackBonuses": [{"class": "unique", "bonus": 12}],
    "armorClasses": ["infantry", "unique"],
    "cost": { "food": 60, "wood": 0, "gold": 30 },
    "trainingTime": 9,
    "unique_to": "japanese"
  },
  {
    "id": "huskarl",
    "name": "Huskarl",
    "class": "infantry",
    "hp": 60,
    "attack": 10,
    "meleeArmor": 0,
    "pierceArmor": 6,
    "range": 0,
    "speed": 1.05,
    "attackBonuses": [{"class": "archer", "bonus": 6}, {"class": "eagle", "bonus": 2}],
    "armorClasses": ["infantry", "unique"],
    "cost": { "food": 52, "wood": 0, "gold": 26 },
    "trainingTime": 16,
    "unique_to": "goths"
  },
  {
    "id": "elite_huskarl",
    "name": "Elite Huskarl",
    "class": "infantry",
    "hp": 70,
    "attack": 12,
    "meleeArmor": 0,
    "pierceArmor": 8,
    "range": 0,
    "speed": 1.05,
    "attackBonuses": [{"class": "archer", "bonus": 10}, {"class": "eagle", "bonus": 3}],
    "armorClasses": ["infantry", "unique"],
    "cost": { "food": 52, "wood": 0, "gold": 26 },
    "trainingTime": 16,
    "unique_to": "goths"
  },
  {
    "id": "janissary",
    "name": "Janissary",
    "class": "archer",
    "hp": 35,
    "attack": 17,
    "meleeArmor": 1,
    "pierceArmor": 0,
    "range": 8,
    "speed": 0.96,
    "attackBonuses": [{"class": "ram", "bonus": 2}],
    "armorClasses": ["archer", "gunpowder", "unique"],
    "cost": { "food": 60, "wood": 0, "gold": 55 },
    "trainingTime": 21,
    "unique_to": "turks",
    "special": "No minimum range"
  },
  {
    "id": "elite_janissary",
    "name": "Elite Janissary",
    "class": "archer",
    "hp": 40,
    "attack": 22,
    "meleeArmor": 2,
    "pierceArmor": 0,
    "range": 8,
    "speed": 0.96,
    "attackBonuses": [{"class": "ram", "bonus": 3}],
    "armorClasses": ["archer", "gunpowder", "unique"],
    "cost": { "food": 60, "wood": 0, "gold": 55 },
    "trainingTime": 21,
    "unique_to": "turks",
    "special": "No minimum range"
  },
  {
    "id": "berserk",
    "name": "Berserk",
    "class": "infantry",
    "hp": 54,
    "attack": 9,
    "meleeArmor": 0,
    "pierceArmor": 1,
    "range": 0,
    "speed": 1.05,
    "attackBonuses": [{"class": "eagle", "bonus": 2}, {"class": "cavalry", "bonus": 2}],
    "armorClasses": ["infantry", "unique"],
    "cost": { "food": 65, "wood": 0, "gold": 25 },
    "trainingTime": 16,
    "unique_to": "vikings",
    "special": "Regenerates HP"
  },
  {
    "id": "elite_berserk",
    "name": "Elite Berserk",
    "class": "infantry",
    "hp": 62,
    "attack": 14,
    "meleeArmor": 2,
    "pierceArmor": 1,
    "range": 0,
    "speed": 1.05,
    "attackBonuses": [{"class": "eagle", "bonus": 3}, {"class": "cavalry", "bonus": 5}],
    "armorClasses": ["infantry", "unique"],
    "cost": { "food": 65, "wood": 0, "gold": 25 },
    "trainingTime": 16,
    "unique_to": "vikings",
    "special": "Regenerates HP faster"
  },
  {
    "id": "war_wagon",
    "name": "War Wagon",
    "class": "archer",
    "hp": 150,
    "attack": 9,
    "meleeArmor": 0,
    "pierceArmor": 3,
    "range": 4,
    "speed": 1.2,
    "attackBonuses": [],
    "armorClasses": ["archer", "cavalry_archer", "cavalry", "unique"],
    "cost": { "food": 0, "wood": 110, "gold": 60 },
    "trainingTime": 25,
    "unique_to": "koreans"
  },
  {
    "id": "elite_war_wagon",
    "name": "Elite War Wagon",
    "class": "archer",
    "hp": 200,
    "attack": 9,
    "meleeArmor": 0,
    "pierceArmor": 4,
    "range": 5,
    "speed": 1.2,
    "attackBonuses": [],
    "armorClasses": ["archer", "cavalry_archer", "cavalry", "unique"],
    "cost": { "food": 0, "wood": 110, "gold": 60 },
    "trainingTime": 25,
    "unique_to": "koreans"
  },
  {
    "id": "plumed_archer",
    "name": "Plumed Archer",
    "class": "archer",
    "hp": 50,
    "attack": 5,
    "meleeArmor": 0,
    "pierceArmor": 1,
    "range": 4,
    "speed": 1.2,
    "attackBonuses": [{"class": "spearman", "bonus": 2}, {"class": "infantry", "bonus": 1}],
    "armorClasses": ["archer", "unique"],
    "cost": { "food": 0, "wood": 46, "gold": 46 },
    "trainingTime": 16,
    "unique_to": "mayans"
  },
  {
    "id": "elite_plumed_archer",
    "name": "Elite Plumed Archer",
    "class": "archer",
    "hp": 65,
    "attack": 5,
    "meleeArmor": 0,
    "pierceArmor": 2,
    "range": 5,
    "speed": 1.2,
    "attackBonuses": [{"class": "spearman", "bonus": 2}, {"class": "infantry", "bonus": 2}],
    "armorClasses": ["archer", "unique"],
    "cost": { "food": 0, "wood": 46, "gold": 46 },
    "trainingTime": 16,
    "unique_to": "mayans"
  },
  {
    "id": "jaguar_warrior",
    "name": "Jaguar Warrior",
    "class": "infantry",
    "hp": 50,
    "attack": 10,
    "meleeArmor": 1,
    "pierceArmor": 1,
    "range": 0,
    "speed": 1.0,
    "attackBonuses": [{"class": "infantry", "bonus": 10}, {"class": "eagle", "bonus": 2}],
    "armorClasses": ["infantry", "unique"],
    "cost": { "food": 60, "wood": 0, "gold": 30 },
    "trainingTime": 17,
    "unique_to": "aztecs"
  },
  {
    "id": "elite_jaguar_warrior",
    "name": "Elite Jaguar Warrior",
    "class": "infantry",
    "hp": 75,
    "attack": 12,
    "meleeArmor": 2,
    "pierceArmor": 1,
    "range": 0,
    "speed": 1.0,
    "attackBonuses": [{"class": "infantry", "bonus": 11}, {"class": "eagle", "bonus": 2}],
    "armorClasses": ["infantry", "unique"],
    "cost": { "food": 60, "wood": 0, "gold": 30 },
    "trainingTime": 17,
    "unique_to": "aztecs"
  },
  {
    "id": "tarkan",
    "name": "Tarkan",
    "class": "cavalry",
    "hp": 100,
    "attack": 8,
    "meleeArmor": 1,
    "pierceArmor": 3,
    "range": 0,
    "speed": 1.35,
    "attackBonuses": [{"class": "building", "bonus": 8}],
    "armorClasses": ["cavalry", "unique"],
    "cost": { "food": 60, "wood": 0, "gold": 60 },
    "trainingTime": 14,
    "unique_to": "huns"
  },
  {
    "id": "elite_tarkan",
    "name": "Elite Tarkan",
    "class": "cavalry",
    "hp": 150,
    "attack": 11,
    "meleeArmor": 1,
    "pierceArmor": 4,
    "range": 0,
    "speed": 1.35,
    "attackBonuses": [{"class": "building", "bonus": 10}],
    "armorClasses": ["cavalry", "unique"],
    "cost": { "food": 60, "wood": 0, "gold": 60 },
    "trainingTime": 14,
    "unique_to": "huns"
  },
  {
    "id": "war_elephant",
    "name": "War Elephant",
    "class": "cavalry",
    "hp": 450,
    "attack": 15,
    "meleeArmor": 1,
    "pierceArmor": 2,
    "range": 0,
    "speed": 0.6,
    "attackBonuses": [{"class": "building", "bonus": 7}],
    "armorClasses": ["cavalry", "war_elephant", "unique"],
    "cost": { "food": 200, "wood": 0, "gold": 75 },
    "trainingTime": 31,
    "unique_to": "persians"
  },
  {
    "id": "elite_war_elephant",
    "name": "Elite War Elephant",
    "class": "cavalry",
    "hp": 600,
    "attack": 20,
    "meleeArmor": 1,
    "pierceArmor": 3,
    "range": 0,
    "speed": 0.6,
    "attackBonuses": [{"class": "building", "bonus": 10}],
    "armorClasses": ["cavalry", "war_elephant", "unique"],
    "cost": { "food": 200, "wood": 0, "gold": 75 },
    "trainingTime": 31,
    "unique_to": "persians"
  },
  {
    "id": "conquistador",
    "name": "Conquistador",
    "class": "archer",
    "hp": 55,
    "attack": 16,
    "meleeArmor": 2,
    "pierceArmor": 2,
    "range": 6,
    "speed": 1.3,
    "attackBonuses": [{"class": "ram", "bonus": 4}],
    "armorClasses": ["archer", "cavalry_archer", "cavalry", "gunpowder", "unique"],
    "cost": { "food": 60, "wood": 0, "gold": 70 },
    "trainingTime": 24,
    "unique_to": "spanish"
  },
  {
    "id": "elite_conquistador",
    "name": "Elite Conquistador",
    "class": "archer",
    "hp": 70,
    "attack": 18,
    "meleeArmor": 2,
    "pierceArmor": 2,
    "range": 6,
    "speed": 1.3,
    "attackBonuses": [{"class": "ram", "bonus": 6}],
    "armorClasses": ["archer", "cavalry_archer", "cavalry", "gunpowder", "unique"],
    "cost": { "food": 60, "wood": 0, "gold": 70 },
    "trainingTime": 24,
    "unique_to": "spanish"
  },
  {
    "id": "chu_ko_nu",
    "name": "Chu Ko Nu",
    "class": "archer",
    "hp": 45,
    "attack": 8,
    "meleeArmor": 0,
    "pierceArmor": 0,
    "range": 4,
    "speed": 0.96,
    "attackBonuses": [{"class": "spearman", "bonus": 2}],
    "armorClasses": ["archer", "unique"],
    "cost": { "food": 0, "wood": 40, "gold": 35 },
    "trainingTime": 19,
    "unique_to": "chinese",
    "special": "Fires multiple bolts"
  },
  {
    "id": "elite_chu_ko_nu",
    "name": "Elite Chu Ko Nu",
    "class": "archer",
    "hp": 50,
    "attack": 8,
    "meleeArmor": 0,
    "pierceArmor": 0,
    "range": 4,
    "speed": 0.96,
    "attackBonuses": [{"class": "spearman", "bonus": 2}],
    "armorClasses": ["archer", "unique"],
    "cost": { "food": 0, "wood": 40, "gold": 35 },
    "trainingTime": 13,
    "unique_to": "chinese",
    "special": "Fires multiple bolts"
  },
  {
    "id": "boyar",
    "name": "Boyar",
    "class": "cavalry",
    "hp": 100,
    "attack": 12,
    "meleeArmor": 4,
    "pierceArmor": 1,
    "range": 0,
    "speed": 1.35,
    "attackBonuses": [],
    "armorClasses": ["cavalry", "unique"],
    "cost": { "food": 50, "wood": 0, "gold": 80 },
    "trainingTime": 15,
    "unique_to": "slavs"
  },
  {
    "id": "elite_boyar",
    "name": "Elite Boyar",
    "class": "cavalry",
    "hp": 130,
    "attack": 14,
    "meleeArmor": 6,
    "pierceArmor": 2,
    "range": 0,
    "speed": 1.35,
    "attackBonuses": [],
    "armorClasses": ["cavalry", "unique"],
    "cost": { "food": 50, "wood": 0, "gold": 80 },
    "trainingTime": 15,
    "unique_to": "slavs"
  },
  {
    "id": "elephant_archer",
    "name": "Elephant Archer",
    "class": "archer",
    "hp": 250,
    "attack": 6,
    "meleeArmor": 0,
    "pierceArmor": 3,
    "range": 4,
    "speed": 0.8,
    "attackBonuses": [],
    "armorClasses": ["archer", "cavalry_archer", "cavalry", "war_elephant", "unique"],
    "cost": { "food": 100, "wood": 0, "gold": 80 },
    "trainingTime": 32,
    "unique_to": "dravidians"
  },
  {
    "id": "elite_elephant_archer",
    "name": "Elite Elephant Archer",
    "class": "archer",
    "hp": 280,
    "attack": 7,
    "meleeArmor": 0,
    "pierceArmor": 3,
    "range": 4,
    "speed": 0.8,
    "attackBonuses": [],
    "armorClasses": ["archer", "cavalry_archer", "cavalry", "war_elephant", "unique"],
    "cost": { "food": 100, "wood": 0, "gold": 80 },
    "trainingTime": 32,
    "unique_to": "dravidians"
  },
  {
    "id": "genoese_crossbowman",
    "name": "Genoese Crossbowman",
    "class": "archer",
    "hp": 45,
    "attack": 6,
    "meleeArmor": 1,
    "pierceArmor": 0,
    "range": 4,
    "speed": 0.96,
    "attackBonuses": [{"class": "cavalry", "bonus": 5}, {"class": "war_elephant", "bonus": 5}, {"class": "camel", "bonus": 4}],
    "armorClasses": ["archer", "unique"],
    "cost": { "food": 0, "wood": 45, "gold": 40 },
    "trainingTime": 22,
    "unique_to": "italians"
  },
  {
    "id": "elite_genoese_crossbowman",
    "name": "Elite Genoese Crossbowman",
    "class": "archer",
    "hp": 50,
    "attack": 6,
    "meleeArmor": 1,
    "pierceArmor": 0,
    "range": 4,
    "speed": 0.96,
    "attackBonuses": [{"class": "cavalry", "bonus": 7}, {"class": "war_elephant", "bonus": 7}, {"class": "camel", "bonus": 6}],
    "armorClasses": ["archer", "unique"],
    "cost": { "food": 0, "wood": 45, "gold": 40 },
    "trainingTime": 22,
    "unique_to": "italians"
  },
  {
    "id": "magyar_huszar",
    "name": "Magyar Huszar",
    "class": "cavalry",
    "hp": 65,
    "attack": 9,
    "meleeArmor": 0,
    "pierceArmor": 2,
    "range": 0,
    "speed": 1.5,
    "attackBonuses": [{"class": "siege", "bonus": 5}],
    "armorClasses": ["cavalry", "unique"],
    "cost": { "food": 80, "wood": 0, "gold": 10 },
    "trainingTime": 16,
    "unique_to": "magyars"
  },
  {
    "id": "elite_magyar_huszar",
    "name": "Elite Magyar Huszar",
    "class": "cavalry",
    "hp": 85,
    "attack": 10,
    "meleeArmor": 0,
    "pierceArmor": 2,
    "range": 0,
    "speed": 1.5,
    "attackBonuses": [{"class": "siege", "bonus": 8}],
    "armorClasses": ["cavalry", "unique"],
    "cost": { "food": 80, "wood": 0, "gold": 10 },
    "trainingTime": 16,
    "unique_to": "magyars"
  },
  {
    "id": "kamayuk",
    "name": "Kamayuk",
    "class": "infantry",
    "hp": 60,
    "attack": 7,
    "meleeArmor": 0,
    "pierceArmor": 0,
    "range": 1,
    "speed": 1.0,
    "attackBonuses": [{"class": "cavalry", "bonus": 8}, {"class": "war_elephant", "bonus": 20}, {"class": "camel", "bonus": 6}],
    "armorClasses": ["infantry", "unique"],
    "cost": { "food": 60, "wood": 0, "gold": 30 },
    "trainingTime": 10,
    "unique_to": "incas"
  },
  {
    "id": "elite_kamayuk",
    "name": "Elite Kamayuk",
    "class": "infantry",
    "hp": 80,
    "attack": 8,
    "meleeArmor": 1,
    "pierceArmor": 0,
    "range": 1,
    "speed": 1.0,
    "attackBonuses": [{"class": "cavalry", "bonus": 12}, {"class": "war_elephant", "bonus": 20}, {"class": "camel", "bonus": 8}],
    "armorClasses": ["infantry", "unique"],
    "cost": { "food": 60, "wood": 0, "gold": 30 },
    "trainingTime": 10,
    "unique_to": "incas"
  },
  {
    "id": "camel_archer",
    "name": "Camel Archer",
    "class": "archer",
    "hp": 55,
    "attack": 7,
    "meleeArmor": 0,
    "pierceArmor": 1,
    "range": 4,
    "speed": 1.4,
    "attackBonuses": [{"class": "cavalry_archer", "bonus": 4}, {"class": "cavalry", "bonus": 2}],
    "armorClasses": ["archer", "cavalry_archer", "cavalry", "camel", "unique"],
    "cost": { "food": 0, "wood": 50, "gold": 60 },
    "trainingTime": 25,
    "unique_to": "berbers"
  },
  {
    "id": "elite_camel_archer",
    "name": "Elite Camel Archer",
    "class": "archer",
    "hp": 60,
    "attack": 8,
    "meleeArmor": 1,
    "pierceArmor": 1,
    "range": 4,
    "speed": 1.4,
    "attackBonuses": [{"class": "cavalry_archer", "bonus": 6}, {"class": "cavalry", "bonus": 2}],
    "armorClasses": ["archer", "cavalry_archer", "cavalry", "camel", "unique"],
    "cost": { "food": 0, "wood": 50, "gold": 60 },
    "trainingTime": 25,
    "unique_to": "berbers"
  },
  {
    "id": "genitour",
    "name": "Genitour",
    "class": "archer",
    "hp": 50,
    "attack": 3,
    "meleeArmor": 0,
    "pierceArmor": 4,
    "range": 4,
    "speed": 1.35,
    "attackBonuses": [{"class": "archer", "bonus": 4}, {"class": "cavalry_archer", "bonus": 2}],
    "armorClasses": ["archer", "cavalry_archer", "cavalry"],
    "cost": { "food": 50, "wood": 35, "gold": 0 },
    "trainingTime": 25,
    "unique_to": "berbers"
  },
  {
    "id": "elite_genitour",
    "name": "Elite Genitour",
    "class": "archer",
    "hp": 55,
    "attack": 4,
    "meleeArmor": 0,
    "pierceArmor": 4,
    "range": 4,
    "speed": 1.35,
    "attackBonuses": [{"class": "archer", "bonus": 5}, {"class": "cavalry_archer", "bonus": 3}],
    "armorClasses": ["archer", "cavalry_archer", "cavalry"],
    "cost": { "food": 50, "wood": 35, "gold": 0 },
    "trainingTime": 25,
    "unique_to": "berbers"
  },
  {
    "id": "gbeto",
    "name": "Gbeto",
    "class": "infantry",
    "hp": 30,
    "attack": 10,
    "meleeArmor": 0,
    "pierceArmor": 0,
    "range": 5,
    "speed": 1.25,
    "attackBonuses": [],
    "armorClasses": ["infantry", "unique"],
    "cost": { "food": 50, "wood": 0, "gold": 40 },
    "trainingTime": 17,
    "unique_to": "malians"
  },
  {
    "id": "elite_gbeto",
    "name": "Elite Gbeto",
    "class": "infantry",
    "hp": 45,
    "attack": 13,
    "meleeArmor": 0,
    "pierceArmor": 0,
    "range": 6,
    "speed": 1.25,
    "attackBonuses": [],
    "armorClasses": ["infantry", "unique"],
    "cost": { "food": 50, "wood": 0, "gold": 40 },
    "trainingTime": 17,
    "unique_to": "malians"
  },
  {
    "id": "shotel_warrior",
    "name": "Shotel Warrior",
    "class": "infantry",
    "hp": 40,
    "attack": 16,
    "meleeArmor": 0,
    "pierceArmor": 0,
    "range": 0,
    "speed": 1.2,
    "attackBonuses": [],
    "armorClasses": ["infantry", "unique"],
    "cost": { "food": 50, "wood": 0, "gold": 30 },
    "trainingTime": 8,
    "unique_to": "ethiopians"
  },
  {
    "id": "elite_shotel_warrior",
    "name": "Elite Shotel Warrior",
    "class": "infantry",
    "hp": 50,
    "attack": 18,
    "meleeArmor": 0,
    "pierceArmor": 0,
    "range": 0,
    "speed": 1.2,
    "attackBonuses": [],
    "armorClasses": ["infantry", "unique"],
    "cost": { "food": 50, "wood": 0, "gold": 30 },
    "trainingTime": 8,
    "unique_to": "ethiopians"
  },
  {
    "id": "ballista_elephant",
    "name": "Ballista Elephant",
    "class": "cavalry",
    "hp": 250,
    "attack": 8,
    "meleeArmor": 0,
    "pierceArmor": 3,
    "range": 5,
    "speed": 0.8,
    "attackBonuses": [{"class": "war_elephant", "bonus": 8}],
    "armorClasses": ["cavalry", "war_elephant", "siege", "unique"],
    "cost": { "food": 100, "wood": 0, "gold": 80 },
    "trainingTime": 25,
    "unique_to": "khmer",
    "special": "Pass-through bolt"
  },
  {
    "id": "elite_ballista_elephant",
    "name": "Elite Ballista Elephant",
    "class": "cavalry",
    "hp": 290,
    "attack": 9,
    "meleeArmor": 0,
    "pierceArmor": 3,
    "range": 5,
    "speed": 0.8,
    "attackBonuses": [{"class": "war_elephant", "bonus": 8}],
    "armorClasses": ["cavalry", "war_elephant", "siege", "unique"],
    "cost": { "food": 100, "wood": 0, "gold": 80 },
    "trainingTime": 25,
    "unique_to": "khmer",
    "special": "Pass-through bolt"
  },
  {
    "id": "karambit_warrior",
    "name": "Karambit Warrior",
    "class": "infantry",
    "hp": 30,
    "attack": 7,
    "meleeArmor": 0,
    "pierceArmor": 1,
    "range": 0,
    "speed": 1.2,
    "attackBonuses": [{"class": "eagle", "bonus": 2}],
    "armorClasses": ["infantry", "unique"],
    "cost": { "food": 25, "wood": 0, "gold": 15 },
    "trainingTime": 6,
    "unique_to": "malay",
    "special": "Only takes 0.5 population"
  },
  {
    "id": "elite_karambit_warrior",
    "name": "Elite Karambit Warrior",
    "class": "infantry",
    "hp": 40,
    "attack": 8,
    "meleeArmor": 0,
    "pierceArmor": 1,
    "range": 0,
    "speed": 1.2,
    "attackBonuses": [{"class": "eagle", "bonus": 2}],
    "armorClasses": ["infantry", "unique"],
    "cost": { "food": 25, "wood": 0, "gold": 15 },
    "trainingTime": 6,
    "unique_to": "malay",
    "special": "Only takes 0.5 population"
  },
  {
    "id": "arambai",
    "name": "Arambai",
    "class": "archer",
    "hp": 60,
    "attack": 12,
    "meleeArmor": 0,
    "pierceArmor": 0,
    "range": 4,
    "speed": 1.3,
    "attackBonuses": [],
    "armorClasses": ["archer", "cavalry_archer", "cavalry", "unique"],
    "cost": { "food": 0, "wood": 75, "gold": 60 },
    "trainingTime": 21,
    "unique_to": "burmese",
    "special": "Very inaccurate (20%)"
  },
  {
    "id": "elite_arambai",
    "name": "Elite Arambai",
    "class": "archer",
    "hp": 65,
    "attack": 15,
    "meleeArmor": 0,
    "pierceArmor": 0,
    "range": 4,
    "speed": 1.3,
    "attackBonuses": [],
    "armorClasses": ["archer", "cavalry_archer", "cavalry", "unique"],
    "cost": { "food": 0, "wood": 75, "gold": 60 },
    "trainingTime": 21,
    "unique_to": "burmese",
    "special": "Very inaccurate (20%)"
  },
  {
    "id": "rattan_archer",
    "name": "Rattan Archer",
    "class": "archer",
    "hp": 40,
    "attack": 6,
    "meleeArmor": 0,
    "pierceArmor": 4,
    "range": 4,
    "speed": 1.1,
    "attackBonuses": [{"class": "spearman", "bonus": 2}],
    "armorClasses": ["archer", "unique"],
    "cost": { "food": 0, "wood": 50, "gold": 45 },
    "trainingTime": 16,
    "unique_to": "vietnamese"
  },
  {
    "id": "elite_rattan_archer",
    "name": "Elite Rattan Archer",
    "class": "archer",
    "hp": 45,
    "attack": 7,
    "meleeArmor": 0,
    "pierceArmor": 6,
    "range": 5,
    "speed": 1.1,
    "attackBonuses": [{"class": "spearman", "bonus": 2}],
    "armorClasses": ["archer", "unique"],
    "cost": { "food": 0, "wood": 50, "gold": 45 },
    "trainingTime": 16,
    "unique_to": "vietnamese"
  },
  {
    "id": "konnik",
    "name": "Konnik",
    "class": "cavalry",
    "hp": 100,
    "attack": 12,
    "meleeArmor": 2,
    "pierceArmor": 1,
    "range": 0,
    "speed": 1.35,
    "attackBonuses": [],
    "armorClasses": ["cavalry", "unique"],
    "cost": { "food": 60, "wood": 0, "gold": 70 },
    "trainingTime": 19,
    "unique_to": "bulgarians",
    "special": "Spawns dismounted Konnik on death"
  },
  {
    "id": "elite_konnik",
    "name": "Elite Konnik",
    "class": "cavalry",
    "hp": 120,
    "attack": 14,
    "meleeArmor": 2,
    "pierceArmor": 2,
    "range": 0,
    "speed": 1.35,
    "attackBonuses": [],
    "armorClasses": ["cavalry", "unique"],
    "cost": { "food": 60, "wood": 0, "gold": 70 },
    "trainingTime": 19,
    "unique_to": "bulgarians",
    "special": "Spawns dismounted Konnik on death"
  },
  {
    "id": "keshik",
    "name": "Keshik",
    "class": "cavalry",
    "hp": 100,
    "attack": 9,
    "meleeArmor": 1,
    "pierceArmor": 2,
    "range": 0,
    "speed": 1.4,
    "attackBonuses": [],
    "armorClasses": ["cavalry", "unique"],
    "cost": { "food": 60, "wood": 0, "gold": 40 },
    "trainingTime": 16,
    "unique_to": "tatars",
    "special": "Generates gold when attacking"
  },
  {
    "id": "elite_keshik",
    "name": "Elite Keshik",
    "class": "cavalry",
    "hp": 120,
    "attack": 11,
    "meleeArmor": 1,
    "pierceArmor": 3,
    "range": 0,
    "speed": 1.4,
    "attackBonuses": [],
    "armorClasses": ["cavalry", "unique"],
    "cost": { "food": 60, "wood": 0, "gold": 40 },
    "trainingTime": 16,
    "unique_to": "tatars",
    "special": "Generates gold when attacking"
  },
  {
    "id": "leitis",
    "name": "Leitis",
    "class": "cavalry",
    "hp": 100,
    "attack": 12,
    "meleeArmor": 1,
    "pierceArmor": 1,
    "range": 0,
    "speed": 1.4,
    "attackBonuses": [],
    "armorClasses": ["cavalry", "unique"],
    "cost": { "food": 70, "wood": 0, "gold": 50 },
    "trainingTime": 20,
    "unique_to": "lithuanians",
    "special": "Ignores melee armor"
  },
  {
    "id": "elite_leitis",
    "name": "Elite Leitis",
    "class": "cavalry",
    "hp": 130,
    "attack": 14,
    "meleeArmor": 2,
    "pierceArmor": 1,
    "range": 0,
    "speed": 1.4,
    "attackBonuses": [],
    "armorClasses": ["cavalry", "unique"],
    "cost": { "food": 70, "wood": 0, "gold": 50 },
    "trainingTime": 20,
    "unique_to": "lithuanians",
    "special": "Ignores melee armor"
  },
  {
    "id": "coustillier",
    "name": "Coustillier",
    "class": "cavalry",
    "hp": 115,
    "attack": 8,
    "meleeArmor": 2,
    "pierceArmor": 2,
    "range": 0,
    "speed": 1.35,
    "attackBonuses": [],
    "armorClasses": ["cavalry", "unique"],
    "cost": { "food": 55, "wood": 0, "gold": 55 },
    "trainingTime": 15,
    "unique_to": "burgundians",
    "special": "Charge attack deals +25 damage"
  },
  {
    "id": "elite_coustillier",
    "name": "Elite Coustillier",
    "class": "cavalry",
    "hp": 145,
    "attack": 12,
    "meleeArmor": 2,
    "pierceArmor": 2,
    "range": 0,
    "speed": 1.35,
    "attackBonuses": [],
    "armorClasses": ["cavalry", "unique"],
    "cost": { "food": 55, "wood": 0, "gold": 55 },
    "trainingTime": 15,
    "unique_to": "burgundians",
    "special": "Charge attack deals +30 damage"
  },
  {
    "id": "flemish_militia",
    "name": "Flemish Militia",
    "class": "infantry",
    "hp": 75,
    "attack": 12,
    "meleeArmor": 1,
    "pierceArmor": 1,
    "range": 0,
    "speed": 1.0,
    "attackBonuses": [{"class": "cavalry", "bonus": 8}, {"class": "camel", "bonus": 6}, {"class": "eagle", "bonus": 4}],
    "armorClasses": ["infantry"],
    "cost": { "food": 60, "wood": 0, "gold": 25 },
    "trainingTime": 14,
    "unique_to": "burgundians"
  },
  {
    "id": "serjeant",
    "name": "Serjeant",
    "class": "infantry",
    "hp": 50,
    "attack": 8,
    "meleeArmor": 2,
    "pierceArmor": 2,
    "range": 0,
    "speed": 0.9,
    "attackBonuses": [],
    "armorClasses": ["infantry", "unique"],
    "cost": { "food": 60, "wood": 0, "gold": 35 },
    "trainingTime": 20,
    "unique_to": "sicilians",
    "special": "Can build Donjons"
  },
  {
    "id": "elite_serjeant",
    "name": "Elite Serjeant",
    "class": "infantry",
    "hp": 75,
    "attack": 11,
    "meleeArmor": 4,
    "pierceArmor": 4,
    "range": 0,
    "speed": 0.9,
    "attackBonuses": [],
    "armorClasses": ["infantry", "unique"],
    "cost": { "food": 60, "wood": 0, "gold": 35 },
    "trainingTime": 20,
    "unique_to": "sicilians",
    "special": "Can build Donjons"
  },
  {
    "id": "obuch",
    "name": "Obuch",
    "class": "infantry",
    "hp": 60,
    "attack": 8,
    "meleeArmor": 0,
    "pierceArmor": 0,
    "range": 0,
    "speed": 1.0,
    "attackBonuses": [],
    "armorClasses": ["infantry", "unique"],
    "cost": { "food": 55, "wood": 0, "gold": 20 },
    "trainingTime": 9,
    "unique_to": "poles",
    "special": "Strips 1 melee/pierce armor per hit"
  },
  {
    "id": "elite_obuch",
    "name": "Elite Obuch",
    "class": "infantry",
    "hp": 70,
    "attack": 10,
    "meleeArmor": 0,
    "pierceArmor": 0,
    "range": 0,
    "speed": 1.0,
    "attackBonuses": [],
    "armorClasses": ["infantry", "unique"],
    "cost": { "food": 55, "wood": 0, "gold": 20 },
    "trainingTime": 9,
    "unique_to": "poles",
    "special": "Strips 2 melee/pierce armor per hit"
  },
  {
    "id": "hussite_wagon",
    "name": "Hussite Wagon",
    "class": "siege",
    "hp": 150,
    "attack": 16,
    "meleeArmor": 0,
    "pierceArmor": 7,
    "range": 6,
    "speed": 0.85,
    "attackBonuses": [],
    "armorClasses": ["siege", "unique"],
    "cost": { "food": 0, "wood": 110, "gold": 70 },
    "trainingTime": 21,
    "unique_to": "bohemians",
    "special": "Shields ranged units behind it"
  },
  {
    "id": "elite_hussite_wagon",
    "name": "Elite Hussite Wagon",
    "class": "siege",
    "hp": 200,
    "attack": 17,
    "meleeArmor": 0,
    "pierceArmor": 8,
    "range": 7,
    "speed": 0.85,
    "attackBonuses": [],
    "armorClasses": ["siege", "unique"],
    "cost": { "food": 0, "wood": 110, "gold": 70 },
    "trainingTime": 21,
    "unique_to": "bohemians",
    "special": "Shields ranged units behind it"
  },
  {
    "id": "houfnice",
    "name": "Houfnice",
    "class": "siege",
    "hp": 80,
    "attack": 50,
    "meleeArmor": 2,
    "pierceArmor": 5,
    "range": 12,
    "speed": 0.7,
    "attackBonuses": [{"class": "building", "bonus": 220}, {"class": "ship", "bonus": 40}, {"class": "siege", "bonus": 20}],
    "armorClasses": ["siege", "gunpowder"],
    "cost": { "food": 0, "wood": 225, "gold": 225 },
    "trainingTime": 56,
    "unique_to": "bohemians",
    "special": "Upgraded Bombard Cannon with blast radius"
  },
  {
    "id": "ghulam",
    "name": "Ghulam",
    "class": "infantry",
    "hp": 55,
    "attack": 8,
    "meleeArmor": 0,
    "pierceArmor": 3,
    "range": 0,
    "speed": 1.0,
    "attackBonuses": [{"class": "archer", "bonus": 4}],
    "armorClasses": ["infantry", "unique"],
    "cost": { "food": 45, "wood": 0, "gold": 40 },
    "trainingTime": 12,
    "unique_to": "hindustanis",
    "special": "Deals pass-through melee damage"
  },
  {
    "id": "elite_ghulam",
    "name": "Elite Ghulam",
    "class": "infantry",
    "hp": 65,
    "attack": 10,
    "meleeArmor": 0,
    "pierceArmor": 4,
    "range": 0,
    "speed": 1.0,
    "attackBonuses": [{"class": "archer", "bonus": 6}],
    "armorClasses": ["infantry", "unique"],
    "cost": { "food": 45, "wood": 0, "gold": 40 },
    "trainingTime": 12,
    "unique_to": "hindustanis",
    "special": "Deals pass-through melee damage"
  },
  {
    "id": "chakram_thrower",
    "name": "Chakram Thrower",
    "class": "infantry",
    "hp": 50,
    "attack": 8,
    "meleeArmor": 1,
    "pierceArmor": 0,
    "range": 3,
    "speed": 1.0,
    "attackBonuses": [{"class": "infantry", "bonus": 2}],
    "armorClasses": ["infantry", "unique"],
    "cost": { "food": 65, "wood": 0, "gold": 30 },
    "trainingTime": 15,
    "unique_to": "gurjaras",
    "special": "Pass-through ranged attack"
  },
  {
    "id": "elite_chakram_thrower",
    "name": "Elite Chakram Thrower",
    "class": "infantry",
    "hp": 60,
    "attack": 10,
    "meleeArmor": 1,
    "pierceArmor": 0,
    "range": 3,
    "speed": 1.0,
    "attackBonuses": [{"class": "infantry", "bonus": 3}],
    "armorClasses": ["infantry", "unique"],
    "cost": { "food": 65, "wood": 0, "gold": 30 },
    "trainingTime": 15,
    "unique_to": "gurjaras",
    "special": "Pass-through ranged attack"
  },
  {
    "id": "ratha",
    "name": "Ratha",
    "class": "cavalry",
    "hp": 105,
    "attack": 6,
    "meleeArmor": 0,
    "pierceArmor": 1,
    "range": 4,
    "speed": 1.3,
    "attackBonuses": [],
    "armorClasses": ["archer", "cavalry_archer", "cavalry", "unique"],
    "cost": { "food": 60, "wood": 0, "gold": 60 },
    "trainingTime": 18,
    "unique_to": "bengalis",
    "special": "Can switch between ranged/melee mode"
  },
  {
    "id": "elite_ratha",
    "name": "Elite Ratha",
    "class": "cavalry",
    "hp": 120,
    "attack": 7,
    "meleeArmor": 1,
    "pierceArmor": 1,
    "range": 4,
    "speed": 1.3,
    "attackBonuses": [],
    "armorClasses": ["archer", "cavalry_archer", "cavalry", "unique"],
    "cost": { "food": 60, "wood": 0, "gold": 60 },
    "trainingTime": 18,
    "unique_to": "bengalis",
    "special": "Can switch between ranged/melee mode"
  },
  {
    "id": "urumi_swordsman",
    "name": "Urumi Swordsman",
    "class": "infantry",
    "hp": 55,
    "attack": 8,
    "meleeArmor": 0,
    "pierceArmor": 1,
    "range": 0,
    "speed": 1.05,
    "attackBonuses": [{"class": "eagle", "bonus": 2}, {"class": "building", "bonus": 4}],
    "armorClasses": ["infantry", "unique"],
    "cost": { "food": 65, "wood": 0, "gold": 20 },
    "trainingTime": 12,
    "unique_to": "dravidians",
    "special": "Charge attack, deals area damage"
  },
  {
    "id": "elite_urumi_swordsman",
    "name": "Elite Urumi Swordsman",
    "class": "infantry",
    "hp": 65,
    "attack": 10,
    "meleeArmor": 0,
    "pierceArmor": 1,
    "range": 0,
    "speed": 1.05,
    "attackBonuses": [{"class": "eagle", "bonus": 3}, {"class": "building", "bonus": 5}],
    "armorClasses": ["infantry", "unique"],
    "cost": { "food": 65, "wood": 0, "gold": 20 },
    "trainingTime": 12,
    "unique_to": "dravidians",
    "special": "Charge attack, deals area damage"
  },
  {
    "id": "centurion",
    "name": "Centurion",
    "class": "cavalry",
    "hp": 110,
    "attack": 13,
    "meleeArmor": 2,
    "pierceArmor": 2,
    "range": 0,
    "speed": 1.35,
    "attackBonuses": [{"class": "infantry", "bonus": 6}],
    "armorClasses": ["cavalry", "unique"],
    "cost": { "food": 60, "wood": 0, "gold": 70 },
    "trainingTime": 18,
    "unique_to": "romans",
    "special": "Heals nearby infantry"
  },
  {
    "id": "elite_centurion",
    "name": "Elite Centurion",
    "class": "cavalry",
    "hp": 140,
    "attack": 15,
    "meleeArmor": 2,
    "pierceArmor": 2,
    "range": 0,
    "speed": 1.35,
    "attackBonuses": [{"class": "infantry", "bonus": 8}],
    "armorClasses": ["cavalry", "unique"],
    "cost": { "food": 60, "wood": 0, "gold": 70 },
    "trainingTime": 18,
    "unique_to": "romans",
    "special": "Heals nearby infantry"
  },
  {
    "id": "legionary",
    "name": "Legionary",
    "class": "infantry",
    "hp": 75,
    "attack": 14,
    "meleeArmor": 1,
    "pierceArmor": 1,
    "range": 0,
    "speed": 0.9,
    "attackBonuses": [{"class": "eagle", "bonus": 8}, {"class": "infantry", "bonus": 6}],
    "armorClasses": ["infantry"],
    "cost": { "food": 60, "wood": 0, "gold": 20 },
    "trainingTime": 21,
    "unique_to": "romans",
    "special": "Charges shield vs ranged attacks"
  },
  {
    "id": "monaspa",
    "name": "Monaspa",
    "class": "cavalry",
    "hp": 100,
    "attack": 11,
    "meleeArmor": 2,
    "pierceArmor": 1,
    "range": 0,
    "speed": 1.4,
    "attackBonuses": [],
    "armorClasses": ["cavalry", "unique"],
    "cost": { "food": 60, "wood": 0, "gold": 55 },
    "trainingTime": 17,
    "unique_to": "georgians",
    "special": "Stronger when grouped with other Monaspa"
  },
  {
    "id": "elite_monaspa",
    "name": "Elite Monaspa",
    "class": "cavalry",
    "hp": 120,
    "attack": 13,
    "meleeArmor": 2,
    "pierceArmor": 1,
    "range": 0,
    "speed": 1.4,
    "attackBonuses": [],
    "armorClasses": ["cavalry", "unique"],
    "cost": { "food": 60, "wood": 0, "gold": 55 },
    "trainingTime": 17,
    "unique_to": "georgians",
    "special": "Stronger when grouped with other Monaspa"
  },
  {
    "id": "composite_bowman",
    "name": "Composite Bowman",
    "class": "archer",
    "hp": 35,
    "attack": 6,
    "meleeArmor": 0,
    "pierceArmor": 1,
    "range": 5,
    "speed": 0.96,
    "attackBonuses": [{"class": "spearman", "bonus": 2}, {"class": "ram", "bonus": 2}],
    "armorClasses": ["archer", "unique"],
    "cost": { "food": 0, "wood": 35, "gold": 45 },
    "trainingTime": 20,
    "unique_to": "armenians"
  },
  {
    "id": "elite_composite_bowman",
    "name": "Elite Composite Bowman",
    "class": "archer",
    "hp": 40,
    "attack": 7,
    "meleeArmor": 0,
    "pierceArmor": 2,
    "range": 5,
    "speed": 0.96,
    "attackBonuses": [{"class": "spearman", "bonus": 3}, {"class": "ram", "bonus": 3}],
    "armorClasses": ["archer", "unique"],
    "cost": { "food": 0, "wood": 35, "gold": 45 },
    "trainingTime": 20,
    "unique_to": "armenians"
  }
]
